kAuth/__init__.py
kauth-1.0.9.dist-info/METADATA
kauth-1.0.9.dist-info/WHEEL
kauth-1.0.9.dist-info/top_level.txt
kauth-1.0.9.dist-info/RECORD
