Metadata-Version: 2.1
Name: kauth
Version: 1.0.9
Summary: Authentication
Home-page: https://github.com/kagepark/kAuth
Author: Kage Park
License: MIT
Platform: UNKNOWN
Classifier: Programming Language :: Python :: 2
Classifier: Programming Language :: Python :: 3
Classifier: License :: OSI Approved :: MIT License
Classifier: Operating System :: OS Independent
